aiomoney/__init__.py
aiomoney/account.py
aiomoney/auth.py
aiomoney/errors.py
aiomoney/http_executor.py
aiomoney/schemas/__init__.py
aiomoney/schemas/account_info.py
aiomoney/schemas/invocie.py
aiomoney/schemas/operation_details.py
aiomoney/schemas/operation_history.py
aiomoney-3.0.2.dist-info/METADATA
aiomoney-3.0.2.dist-info/WHEEL
aiomoney-3.0.2.dist-info/RECORD
