Metadata-Version: 2.1
Name: aiomoney
Version: 3.0.2
Summary: Простая асинхронная библиотека для работы с API ЮMoney
License: MIT
Keywords: yoomoney,python,async
Author: fofmow
Author-email: fofmow@gmail.com
Requires-Python: >=3.12,<4.0
Classifier: License :: OSI Approved :: MIT License
Classifier: Operating System :: OS Independent
Classifier: Programming Language :: Python :: 3
Classifier: Programming Language :: Python :: 3.12
Classifier: Programming Language :: Python :: 3.13
Classifier: Programming Language :: Python :: 3.10
Requires-Dist: aiohttp (>=3.11.9,<4.0.0)
Requires-Dist: pydantic (>=2.10.3,<3.0.0)
Project-URL: homepage, https://github.com/fofmow/aiomoney
Project-URL: repository, https://github.com/fofmow/aiomoney
